coastviewer/__init__.py
coastviewer/cli.py
coastviewer/coastviewer.py
coastviewer/controllers.py
coastviewer/datasets.py
coastviewer/extra_cm.py
coastviewer/plots.py
coastviewer/utils.py
coastviewer/swagger/swagger.yaml
coastviewer/templates/info-table.html
coastviewer/templates/info.html
coastviewer/templates/lod.kml
coastviewer/templates/main.html
coastviewer/templates/placemark.html
coastviewer/templates/styles.kml
coastviewer/templates/transect.kml
coastviewer-0.1.12.dist-info/DESCRIPTION.rst
coastviewer-0.1.12.dist-info/METADATA
coastviewer-0.1.12.dist-info/RECORD
coastviewer-0.1.12.dist-info/WHEEL
coastviewer-0.1.12.dist-info/entry_points.txt
coastviewer-0.1.12.dist-info/metadata.json
coastviewer-0.1.12.dist-info/top_level.txt
