Metadata-Version: 2.0
Name: coastviewer
Version: 0.1.12
Summary: Coast Viewer, the backend for the coast viewer. A tool to visualize coastal data.
Home-page: https://github.com/openearth/coastviewer
Author: Fedor Baart
Author-email: fedor.baart@deltares.nl
License: GNU General Public License v3
Keywords: coastviewer
Platform: UNKNOWN
Classifier: Development Status :: 2 - Pre-Alpha
Classifier: Intended Audience :: Developers
Classifier: License :: OSI Approved :: GNU General Public License v3 (GPLv3)
Classifier: Natural Language :: English
Classifier: Programming Language :: Python :: 2
Classifier: Programming Language :: Python :: 2.7
Classifier: Programming Language :: Python :: 3
Classifier: Programming Language :: Python :: 3.5
Classifier: Programming Language :: Python :: 3.6
Requires-Dist: Click (>=6.0)
